{
  "_id": "tkdzKqyfg3DKUlGt",
  "name": "Weapon Mount, Advanced",
  "type": "armorFitting",
  "img": "icons/svg/upgrade.svg",
  "effects": [],
  "system": {
    "description": "<p>As Basic; man-portable heavy OK; slugthrowers 4 magazines; +3 hit and damage.</p>",
    "tl": 4,
    "mass": 2,
    "power": 1,
    "cost": 20000,
    "stackable": true,
    "disabled": false,
    "integral": false,
    "effectId": "weaponMountAdvanced",
    "mountWeaponId": "",
    "damageRoll": "",
    "save": "",
    "healing": false,
    "isWeapon": false,
    "weaponBonus": 0,
    "melee": true,
    "missile": false,
    "score": "str",
    "linkedSkill": "",
    "shock": {
      "damage": "",
      "ac": 0
    },
    "trauma": {
      "die": "",
      "rating": 0
    }
  },
  "ownership": {
    "default": 0
  },
  "folder": "QA2aggShGFYJek4j",
  "sort": 52,
  "_stats": {
    "systemId": "wwn",
    "systemVersion": null,
    "coreVersion": null,
    "createdTime": null,
    "modifiedTime": null,
    "lastModifiedBy": null
  },
  "_key": "!items!tkdzKqyfg3DKUlGt"
}
