{
  "name": "Living Statue, Rock",
  "type": "monster",
  "img": "icons/svg/cowled.svg",
  "items": [
    {
      "_id": "oSxAg5frVRMJlH33",
      "name": "Magma Jet",
      "type": "weapon",
      "img": "systems/wwn/assets/icons/items/weapon.png",
      "sort": 0,
      "flags": {},
      "effects": [],
      "system": {
        "description": "",
        "damage": "2d6",
        "bonus": 0,
        "skillDamage": false,
        "shock": {
          "damage": "2",
          "ac": 18
        },
        "trauma": {
          "die": "1d6",
          "rating": 2
        },
        "skillId": "",
        "skillFallback": "punch",
        "score": "str",
        "melee": true,
        "missile": false,
        "slow": false,
        "burst": false,
        "range": {
          "short": 0,
          "medium": 0,
          "long": 0
        },
        "save": "",
        "tags": [],
        "ammoId": "",
        "charges": {
          "value": 0,
          "max": 0
        },
        "counter": {
          "value": 2,
          "max": 2
        },
        "price": 0,
        "weight": 0,
        "quantity": 1,
        "equipped": false,
        "stowed": false,
        "weightless": "",
        "containerId": "",
        "ammoMode": "none",
        "ammoFallback": ""
      },
      "_key": "!actors.items!2uxvQzVYuXtGnD7G.oSxAg5frVRMJlH33"
    },
    {
      "_id": "OyO6snNt7likoKjH",
      "name": "Sleep Immunity",
      "type": "power",
      "img": "systems/wwn/assets/icons/items/ability.png",
      "sort": 0,
      "flags": {},
      "effects": [],
      "system": {
        "subType": "ability",
        "description": "<p>Unaffected by sleep spells.</p>",
        "commitmentOptions": [
          {
            "cost": 0,
            "length": "none",
            "note": ""
          }
        ],
        "poolCommitted": {
          "none": 0,
          "active": 0,
          "scene": 0,
          "day": 0
        },
        "internalResource": {
          "value": 0,
          "max": 0
        },
        "internalResourceLength": "scene",
        "activation": {
          "roll": "",
          "rollType": "result",
          "rollTarget": 0,
          "save": "",
          "range": "",
          "duration": ""
        }
      },
      "_key": "!actors.items!2uxvQzVYuXtGnD7G.OyO6snNt7likoKjH"
    },
    {
      "_id": "CZ2jrei6Q9nWubeX",
      "name": "Magical Origins",
      "type": "power",
      "img": "systems/wwn/assets/icons/items/ability.png",
      "sort": 0,
      "flags": {},
      "effects": [],
      "system": {
        "subType": "ability",
        "description": "<p>Created by powerful wizards.</p>",
        "commitmentOptions": [
          {
            "cost": 0,
            "length": "none",
            "note": ""
          }
        ],
        "poolCommitted": {
          "none": 0,
          "active": 0,
          "scene": 0,
          "day": 0
        },
        "internalResource": {
          "value": 0,
          "max": 0
        },
        "internalResourceLength": "scene",
        "activation": {
          "roll": "",
          "rollType": "result",
          "rollTarget": 0,
          "save": "",
          "range": "",
          "duration": ""
        }
      },
      "_key": "!actors.items!2uxvQzVYuXtGnD7G.CZ2jrei6Q9nWubeX"
    }
  ],
  "effects": [],
  "flags": {
    "core": {
      "sourceId": "Compendium.wwn.ose-monsters.5jWosa2UFb7abetJ"
    }
  },
  "system": {
    "hp": {
      "value": 23,
      "max": 23
    },
    "strain": {
      "value": 0
    },
    "alienation": {
      "value": 0
    },
    "stress": {
      "value": 0
    },
    "hd": "5d8",
    "skill": 1,
    "details": {
      "alignment": "Neutral",
      "xp": 425,
      "morale": 11,
      "instinct": 5,
      "instinctTable": null,
      "appearing": {
        "d": "1d3",
        "w": "1d3"
      },
      "treasure": {
        "table": "",
        "type": ""
      }
    },
    "favorites": [
      "oSxAg5frVRMJlH33"
    ],
    "notes": "",
    "combat": {
      "ab": 5,
      "damageBonus": 0,
      "damageBonusHalfLevel": false,
      "acManual": {
        "melee": 16,
        "ranged": 16
      }
    },
    "movement": {
      "base": {
        "value": 20
      }
    },
    "biography": "<p>Animated statues of any size and material (three types described below; others may be invented by the referee).</p>"
  },
  "prototypeToken": {
    "name": "Rock Living Statue",
    "displayName": 30,
    "actorLink": false,
    "width": 1,
    "height": 1,
    "lockRotation": false,
    "rotation": 0,
    "alpha": 1,
    "light": {
      "alpha": 0.5,
      "angle": 360,
      "bright": 0,
      "coloration": 1,
      "dim": 0,
      "luminosity": 0.5,
      "saturation": 0,
      "contrast": 0,
      "shadows": 0,
      "animation": {
        "speed": 5,
        "intensity": 5,
        "reverse": false,
        "type": null
      },
      "darkness": {
        "min": 0,
        "max": 1
      },
      "color": null,
      "attenuation": 0.5
    },
    "disposition": -1,
    "displayBars": 20,
    "bar1": {
      "attribute": "hp"
    },
    "bar2": {
      "attribute": "classes.effort1"
    },
    "flags": {
      "image-hover": {
        "hideArt": false
      }
    },
    "randomImg": true,
    "texture": {
      "src": "icons/svg/cowled.svg",
      "tint": null,
      "scaleX": 1,
      "scaleY": 1,
      "offsetX": 0,
      "offsetY": 0,
      "rotation": 0
    },
    "sight": {
      "angle": 360,
      "enabled": false,
      "range": 0,
      "brightness": 1,
      "visionMode": "basic",
      "color": null,
      "attenuation": 0.1,
      "saturation": 0,
      "contrast": 0
    },
    "detectionModes": [],
    "prependAdjective": true
  },
  "_stats": {
    "systemId": "wwn",
    "systemVersion": null,
    "coreVersion": null,
    "createdTime": 1668738330865,
    "modifiedTime": null,
    "lastModifiedBy": null
  },
  "folder": null,
  "sort": 0,
  "ownership": {
    "default": 0
  },
  "_id": "2uxvQzVYuXtGnD7G",
  "_key": "!actors!2uxvQzVYuXtGnD7G"
}
